README.md
setup.py
remo_tools/__init__.py
remo_tools/data_tools.py
remo_tools.egg-info/PKG-INFO
remo_tools.egg-info/SOURCES.txt
remo_tools.egg-info/dependency_links.txt
remo_tools.egg-info/not-zip-safe
remo_tools.egg-info/top_level.txt