Metadata-Version: 1.0
Name: remo-tools
Version: 0.1
Summary: Data tools that helps in data processing
Home-page: UNKNOWN
Author: UNKNOWN
Author-email: UNKNOWN
License: UNKNOWN
Platform: UNKNOWN
